app/__init__.py
app/config.py
app/database.py
app/main.py
app/models.py
app/oauth2.py
app/routers/auth.py
app/routers/url.py
app/routers/user.py
app/schemas.py
app/utils.py
cli/__init__.py
cli/auth.py
cli/main.py
cli/url.py
cli/user.py
cli/utils.py
clip_cli-0.5.0.dist-info/entry_points.txt
clip_cli-0.5.0.dist-info/LICENSE
clip_cli-0.5.0.dist-info/METADATA
clip_cli-0.5.0.dist-info/WHEEL
clip_cli-0.5.0.dist-info/RECORD
