Metadata-Version: 2.3
Name: clip-cli
Version: 0.5.0
Summary: A simple url-shortening tool
License: MIT
Keywords: cli,clip,productivity,automation,typer
Author: Ankita Verma
Author-email: ankita.av.934@gmail.com
Requires-Python: >=3.12
Classifier: License :: OSI Approved :: MIT License
Classifier: Programming Language :: Python :: 3
Classifier: Programming Language :: Python :: 3.12
Classifier: Programming Language :: Python :: 3.13
Requires-Dist: alembic (>=1.16.1,<2.0.0)
Requires-Dist: fastapi[all] (>=0.115.12,<0.116.0)
Requires-Dist: passlib[bcrypt] (>=1.7.4,<2.0.0)
Requires-Dist: psycopg2 (>=2.9.10,<3.0.0)
Requires-Dist: python-jose (>=3.5.0,<4.0.0)
Requires-Dist: sqlalchemy (==1.4)
Project-URL: Documentation, https://github.com/ankita311/clip#readme
Project-URL: Homepage, https://github.com/ankita311/clip
Project-URL: Repository, https://github.com/ankita311/clip
